blindllm/__init__.py
blindllm/ano.py
blindllm/core.py
blindllm/services/__init__.py
blindllm/services/base.py
blindllm/services/claude_service.py
blindllm/services/mistral_service.py
blindllm/services/openai_service.py
blindllm-0.1.0.dist-info/LICENSE
blindllm-0.1.0.dist-info/METADATA
blindllm-0.1.0.dist-info/WHEEL
blindllm-0.1.0.dist-info/top_level.txt
blindllm-0.1.0.dist-info/RECORD
