Metadata-Version: 2.2
Name: blindllm
Version: 0.1.0
Summary: A library for making anonymized calls to LLM APIs
Home-page: https://github.com/EthanPasquier/BlindLLM
Author: BlindLLM Team
Author-email: contact@blindllm.com
Keywords: llm,ai,anonymization,privacy,openai,mistral,claude
Classifier: Development Status :: 3 - Alpha
Classifier: Intended Audience :: Developers
Classifier: License :: OSI Approved :: MIT License
Classifier: Programming Language :: Python :: 3
Classifier: Programming Language :: Python :: 3.8
Classifier: Programming Language :: Python :: 3.9
Classifier: Programming Language :: Python :: 3.10
Classifier: Programming Language :: Python :: 3.11
Requires-Python: >=3.8
License-File: LICENSE
Requires-Dist: openai>=1.0.0
Requires-Dist: anthropic>=0.18.0
Requires-Dist: mistralai
Requires-Dist: text_anonymizer
Dynamic: author
Dynamic: author-email
Dynamic: classifier
Dynamic: description
Dynamic: description-content-type
Dynamic: home-page
Dynamic: keywords
Dynamic: requires-dist
Dynamic: requires-python
Dynamic: summary
